covigator/__init__.py
covigator/command_line.py
covigator/configuration.py
covigator/exceptions.py
covigator/wsgi.py
covigator/accessor/__init__.py
covigator/accessor/abstract_accessor.py
covigator/accessor/covid19_portal_accessor.py
covigator/accessor/ena_accessor.py
covigator/dashboard/__init__.py
covigator/dashboard/dashboard.py
covigator/dashboard/assets/2021_twitter_logo_blue.png
covigator/dashboard/assets/CV19DP_logo_oneliner2.svg
covigator/dashboard/assets/CoVigator_ico.png
covigator/dashboard/assets/CoVigator_logo.png
covigator/dashboard/assets/CoVigator_logo_ENA.png
covigator/dashboard/assets/CoVigator_logo_txt.png
covigator/dashboard/assets/CoVigator_logo_txt_nobg.png
covigator/dashboard/assets/CoVigator_logo_txt_reg.png
covigator/dashboard/assets/CoVigator_logo_txt_reg_no_bg.png
covigator/dashboard/assets/CoVigator_logo_txt_reg_no_bg_covid19_portal.png
covigator/dashboard/assets/CoVigator_logo_txt_reg_no_bg_covid19_portal.xcf
covigator/dashboard/assets/CoVigator_logo_txt_reg_no_bg_ena.xcf
covigator/dashboard/assets/ENA_logo_2021.png
covigator/dashboard/assets/ENA_logo_2021_wo_text.png
covigator/dashboard/assets/favicon.ico
covigator/dashboard/assets/favicon___.ico
covigator/dashboard/assets/resizing_script.js
covigator/dashboard/assets/s1.css
covigator/dashboard/assets/styles.css
covigator/dashboard/assets/tron_logo.png
covigator/dashboard/assets/tron_logo_no_bg.png
covigator/dashboard/assets/tron_logo_without_text.png
covigator/dashboard/assets/wordcloud.png
covigator/dashboard/figures/__init__.py
covigator/dashboard/figures/figures.py
covigator/dashboard/figures/intrahost_mutations.py
covigator/dashboard/figures/lineages.py
covigator/dashboard/figures/mutation_stats.py
covigator/dashboard/figures/recurrent_mutations.py
covigator/dashboard/figures/samples.py
covigator/dashboard/tabs/__init__.py
covigator/dashboard/tabs/acknowledgements.py
covigator/dashboard/tabs/dataset_covid19_portal.py
covigator/dashboard/tabs/dataset_ena.py
covigator-2.2.3.dist-info/LICENSE
covigator-2.2.3.dist-info/METADATA
covigator-2.2.3.dist-info/WHEEL
covigator-2.2.3.dist-info/entry_points.txt
covigator-2.2.3.dist-info/top_level.txt
covigator-2.2.3.dist-info/RECORD
