Metadata-Version: 2.1
Name: covigator
Version: 2.2.3
Home-page: 
Author: TRON - Translational Oncology at the University Medical Center of the Johannes Gutenberg University Mainz - Computational Medicine group
Author-email: patrick.sorn@tron-mainz.de
Classifier: Development Status :: 5 - Production/Stable
Classifier: Intended Audience :: Healthcare Industry
Classifier: Intended Audience :: Science/Research
Classifier: Topic :: Scientific/Engineering :: Bio-Informatics
Classifier: Programming Language :: Python :: 3.8
License-File: LICENSE
Requires-Dist: numpy ==1.22.0
Requires-Dist: pandas ==1.3.3
Requires-Dist: requests ==2.31.0
Requires-Dist: sqlalchemy ==1.3.20
Requires-Dist: dask[complete] ==2022.9.2
Requires-Dist: dask-jobqueue ==0.8.1
Requires-Dist: distributed ==2022.9.2
Requires-Dist: Werkzeug ==2.3.8
Requires-Dist: cytoolz ==0.11.0
Requires-Dist: logzero ==1.6.3
Requires-Dist: psycopg2-binary ==2.8.6
Requires-Dist: plotly ==5.18.0
Requires-Dist: dash ==2.14.1
Requires-Dist: dash-bootstrap-components ==1.5.0
Requires-Dist: cyvcf2 ==0.30.4
Requires-Dist: pycountry ==20.7.3
Requires-Dist: pycountry-convert ==0.7.2
Requires-Dist: tenacity ==6.3.1
Requires-Dist: dash-bio ==0.6.1
Requires-Dist: faker ==8.8.0
Requires-Dist: colorlover ==0.3.0
Requires-Dist: biopython ==1.76
Requires-Dist: lz4 ==3.1.3
Requires-Dist: scikit-bio ==0.5.6
Requires-Dist: ipywidgets ==7.6.3
Requires-Dist: ipython ==8.12
Requires-Dist: parameterized ==0.8.1
